{
    "/js/app.js": "/js/app.js",
    "/css/app.css": "/css/app.css",
    "/css/grayscaleTheme.css": "/css/grayscaleTheme.css",
    "/css/lightTheme.css": "/css/lightTheme.css",
    "/css/draculaTheme.css": "/css/draculaTheme.css",
    "/css/darkTheme.css": "/css/darkTheme.css",
    "/css/bootstrap.css": "/css/bootstrap.css",
    "/css/unicornTheme.css": "/css/unicornTheme.css",
    "/css/halloweenTheme.css": "/css/halloweenTheme.css",
    "/fonts/fontawesome-webfont.eot": "/fonts/fontawesome-webfont.eot",
    "/fonts/fontawesome-webfont.svg": "/fonts/fontawesome-webfont.svg",
    "/fonts/fontawesome-webfont.ttf": "/fonts/fontawesome-webfont.ttf",
    "/fonts/fontawesome-webfont.woff": "/fonts/fontawesome-webfont.woff",
    "/fonts/fontawesome-webfont.woff2": "/fonts/fontawesome-webfont.woff2",
    "/fonts/FontAwesome.otf": "/fonts/FontAwesome.otf"
}
